fycli/__init__.py
fycli/__main__.py
fycli/argparser.py
fycli/cli.py
fycli/dependencies/cli.py
fycli/dependencies/dependencies.py
fycli/environment/__init__.py
fycli/environment/cli.py
fycli/environment/environment.py
fycli/header.txt
fycli/infra/__init__.py
fycli/infra/cli.py
fycli/kubernetes/__init__.py
fycli/kubernetes/cli.py
fycli/module/__init__.py
fycli/module/cli.py
fycli/opa/__init__.py
fycli/opa/cli.py
fycli/opa/opa.py
fycli/skeleton/__init__.py
fycli/skeleton/cli.py
fycli/skeleton/skeleton.py
fycli/terraform/__init__.py
fycli/terraform/terraform.py
fycli/version.py
fycli-3.4.7.dist-info/LICENSE
fycli-3.4.7.dist-info/METADATA
fycli-3.4.7.dist-info/WHEEL
fycli-3.4.7.dist-info/entry_points.txt
fycli-3.4.7.dist-info/RECORD
