Metadata-Version: 2.1
Name: fycli
Version: 3.4.7
Summary: 
Author: Rob Wilson
Author-email: roobert@gmail.com
Requires-Python: >=3.9,<4.0
Classifier: Programming Language :: Python :: 3
Classifier: Programming Language :: Python :: 3.9
Classifier: Programming Language :: Python :: 3.10
Classifier: Programming Language :: Python :: 3.11
Classifier: Programming Language :: Python :: 3.12
Requires-Dist: Jinja2 (>=3.0.3,<4.0.0)
Requires-Dist: google-cloud-storage (>=2.7.0,<3.0.0)
Requires-Dist: packaging (>=24.1,<25.0)
Requires-Dist: pyyaml (>=6.0.1,<7.0.0)
Requires-Dist: rich (>=13.3.2,<14.0.0)
Requires-Dist: semver (>=2.13.0,<3.0.0)
Requires-Dist: sh (>=1.12.14,<2.0.0)
